{
  "collection": [
    {
      "sentence": "não resultou no porto voou no benfica e agora vale 120 milhões ",
      "words": [
        { "word": "não", "tf": 0.08333333333333333, "idf": 1.7634279935629373 },
        {
          "word": "resultou",
          "tf": 0.08333333333333333,
          "idf": 2.0644579892269186
        },
        { "word": "no", "tf": 0.16666666666666666, "idf": 1.7634279935629373 },
        {
          "word": "porto",
          "tf": 0.08333333333333333,
          "idf": 2.0644579892269186
        },
        {
          "word": "voou",
          "tf": 0.08333333333333333,
          "idf": 2.0644579892269186
        },
        {
          "word": "benfica",
          "tf": 0.08333333333333333,
          "idf": 1.7634279935629373
        },
        { "word": "e", "tf": 0.08333333333333333, "idf": 1.3654879848908996 },
        {
          "word": "agora",
          "tf": 0.08333333333333333,
          "idf": 2.0644579892269186
        },
        {
          "word": "vale",
          "tf": 0.08333333333333333,
          "idf": 2.0644579892269186
        },
        { "word": "120", "tf": 0.08333333333333333, "idf": 2.0644579892269186 },
        {
          "word": "milhões",
          "tf": 0.08333333333333333,
          "idf": 1.7634279935629373
        }
      ]
    },
    {
      "sentence": "cláusula batida benfica recebe proposta de 126 milhões por félix",
      "words": [
        { "word": "cláusula", "tf": 0.1, "idf": 2.0644579892269186 },
        { "word": "batida", "tf": 0.1, "idf": 2.0644579892269186 },
        { "word": "benfica", "tf": 0.1, "idf": 1.7634279935629373 },
        { "word": "recebe", "tf": 0.1, "idf": 2.0644579892269186 },
        { "word": "proposta", "tf": 0.1, "idf": 2.0644579892269186 },
        { "word": "de", "tf": 0.1, "idf": 1.587336734507256 },
        { "word": "126", "tf": 0.1, "idf": 2.0644579892269186 },
        { "word": "milhões", "tf": 0.1, "idf": 1.7634279935629373 },
        { "word": "por", "tf": 0.1, "idf": 2.0644579892269186 },
        { "word": "félix", "tf": 0.1, "idf": 2.0644579892269186 }
      ]
    },
    {
      "sentence": "a amazónia é minha mãe",
      "words": [
        { "word": "a", "tf": 0.2, "idf": 1.3654879848908996 },
        { "word": "amazónia", "tf": 0.2, "idf": 2.0644579892269186 },
        { "word": "é", "tf": 0.2, "idf": 1.587336734507256 },
        { "word": "minha", "tf": 0.2, "idf": 2.0644579892269186 },
        { "word": "mãe", "tf": 0.2, "idf": 2.0644579892269186 }
      ]
    },
    {
      "sentence": "portugal na grelha para rir e incomodar muita gente",
      "words": [
        {
          "word": "portugal",
          "tf": 0.1111111111111111,
          "idf": 1.2863067388432747
        },
        { "word": "na", "tf": 0.1111111111111111, "idf": 1.7634279935629373 },
        {
          "word": "grelha",
          "tf": 0.1111111111111111,
          "idf": 2.0644579892269186
        },
        { "word": "para", "tf": 0.1111111111111111, "idf": 1.3654879848908996 },
        { "word": "rir", "tf": 0.1111111111111111, "idf": 2.0644579892269186 },
        { "word": "e", "tf": 0.1111111111111111, "idf": 1.3654879848908996 },
        {
          "word": "incomodar",
          "tf": 0.1111111111111111,
          "idf": 2.0644579892269186
        },
        {
          "word": "muita",
          "tf": 0.1111111111111111,
          "idf": 2.0644579892269186
        },
        { "word": "gente", "tf": 0.1111111111111111, "idf": 2.0644579892269186 }
      ]
    },
    {
      "sentence": "usou contas de mortos para enganar banco onde trabalhava",
      "words": [
        { "word": "usou", "tf": 0.1111111111111111, "idf": 2.0644579892269186 },
        {
          "word": "contas",
          "tf": 0.1111111111111111,
          "idf": 2.0644579892269186
        },
        { "word": "de", "tf": 0.1111111111111111, "idf": 1.587336734507256 },
        {
          "word": "mortos",
          "tf": 0.1111111111111111,
          "idf": 2.0644579892269186
        },
        { "word": "para", "tf": 0.1111111111111111, "idf": 1.3654879848908996 },
        {
          "word": "enganar",
          "tf": 0.1111111111111111,
          "idf": 2.0644579892269186
        },
        {
          "word": "banco",
          "tf": 0.1111111111111111,
          "idf": 2.0644579892269186
        },
        { "word": "onde", "tf": 0.1111111111111111, "idf": 2.0644579892269186 },
        {
          "word": "trabalhava",
          "tf": 0.1111111111111111,
          "idf": 2.0644579892269186
        }
      ]
    },
    {
      "sentence": "mais uma medalha para portugal fu yu é ouro no ténis de mesa ",
      "words": [
        {
          "word": "mais",
          "tf": 0.07692307692307693,
          "idf": 2.0644579892269186
        },
        { "word": "uma", "tf": 0.07692307692307693, "idf": 2.0644579892269186 },
        {
          "word": "medalha",
          "tf": 0.07692307692307693,
          "idf": 2.0644579892269186
        },
        {
          "word": "para",
          "tf": 0.07692307692307693,
          "idf": 1.3654879848908996
        },
        {
          "word": "portugal",
          "tf": 0.07692307692307693,
          "idf": 1.2863067388432747
        },
        { "word": "fu", "tf": 0.07692307692307693, "idf": 2.0644579892269186 },
        { "word": "yu", "tf": 0.07692307692307693, "idf": 2.0644579892269186 },
        { "word": "é", "tf": 0.07692307692307693, "idf": 1.587336734507256 },
        {
          "word": "ouro",
          "tf": 0.07692307692307693,
          "idf": 1.7634279935629373
        },
        { "word": "no", "tf": 0.07692307692307693, "idf": 1.7634279935629373 },
        {
          "word": "ténis",
          "tf": 0.07692307692307693,
          "idf": 2.0644579892269186
        },
        { "word": "de", "tf": 0.07692307692307693, "idf": 1.587336734507256 },
        { "word": "mesa", "tf": 0.07692307692307693, "idf": 2.0644579892269186 }
      ]
    },
    {
      "sentence": "privados na saúde não são um bicho papão para o governo",
      "words": [
        {
          "word": "privados",
          "tf": 0.09090909090909091,
          "idf": 2.0644579892269186
        },
        { "word": "na", "tf": 0.09090909090909091, "idf": 1.7634279935629373 },
        {
          "word": "saúde",
          "tf": 0.09090909090909091,
          "idf": 2.0644579892269186
        },
        { "word": "não", "tf": 0.09090909090909091, "idf": 1.7634279935629373 },
        { "word": "são", "tf": 0.09090909090909091, "idf": 2.0644579892269186 },
        { "word": "um", "tf": 0.09090909090909091, "idf": 1.7634279935629373 },
        {
          "word": "bicho",
          "tf": 0.09090909090909091,
          "idf": 2.0644579892269186
        },
        {
          "word": "papão",
          "tf": 0.09090909090909091,
          "idf": 2.0644579892269186
        },
        {
          "word": "para",
          "tf": 0.09090909090909091,
          "idf": 1.3654879848908996
        },
        { "word": "o", "tf": 0.09090909090909091, "idf": 1.2863067388432747 },
        {
          "word": "governo",
          "tf": 0.09090909090909091,
          "idf": 2.0644579892269186
        }
      ]
    },
    {
      "sentence": "o inferno está a chegar à europa calor extremo pode ser mortal",
      "words": [
        { "word": "o", "tf": 0.08333333333333333, "idf": 1.2863067388432747 },
        {
          "word": "inferno",
          "tf": 0.08333333333333333,
          "idf": 2.0644579892269186
        },
        {
          "word": "está",
          "tf": 0.08333333333333333,
          "idf": 1.7634279935629373
        },
        { "word": "a", "tf": 0.08333333333333333, "idf": 1.3654879848908996 },
        {
          "word": "chegar",
          "tf": 0.08333333333333333,
          "idf": 2.0644579892269186
        },
        { "word": "à", "tf": 0.08333333333333333, "idf": 2.0644579892269186 },
        {
          "word": "europa",
          "tf": 0.08333333333333333,
          "idf": 2.0644579892269186
        },
        {
          "word": "calor",
          "tf": 0.08333333333333333,
          "idf": 2.0644579892269186
        },
        {
          "word": "extremo",
          "tf": 0.08333333333333333,
          "idf": 2.0644579892269186
        },
        {
          "word": "pode",
          "tf": 0.08333333333333333,
          "idf": 2.0644579892269186
        },
        { "word": "ser", "tf": 0.08333333333333333, "idf": 2.0644579892269186 },
        {
          "word": "mortal",
          "tf": 0.08333333333333333,
          "idf": 2.0644579892269186
        }
      ]
    },
    {
      "sentence": "sinto-me feliz e é como se fossem os primeiros momentos quando tinha 18 anos",
      "words": [
        {
          "word": "sinto-me",
          "tf": 0.07142857142857142,
          "idf": 2.0644579892269186
        },
        {
          "word": "feliz",
          "tf": 0.07142857142857142,
          "idf": 2.0644579892269186
        },
        { "word": "e", "tf": 0.07142857142857142, "idf": 1.3654879848908996 },
        { "word": "é", "tf": 0.07142857142857142, "idf": 1.587336734507256 },
        {
          "word": "como",
          "tf": 0.07142857142857142,
          "idf": 2.0644579892269186
        },
        { "word": "se", "tf": 0.07142857142857142, "idf": 2.0644579892269186 },
        {
          "word": "fossem",
          "tf": 0.07142857142857142,
          "idf": 2.0644579892269186
        },
        { "word": "os", "tf": 0.07142857142857142, "idf": 2.0644579892269186 },
        {
          "word": "primeiros",
          "tf": 0.07142857142857142,
          "idf": 2.0644579892269186
        },
        {
          "word": "momentos",
          "tf": 0.07142857142857142,
          "idf": 2.0644579892269186
        },
        {
          "word": "quando",
          "tf": 0.07142857142857142,
          "idf": 2.0644579892269186
        },
        {
          "word": "tinha",
          "tf": 0.07142857142857142,
          "idf": 2.0644579892269186
        },
        { "word": "18", "tf": 0.07142857142857142, "idf": 2.0644579892269186 },
        { "word": "anos", "tf": 0.07142857142857142, "idf": 2.0644579892269186 }
      ]
    },
    {
      "sentence": "esta equipa marca o futuro o futuro está assegurado",
      "words": [
        { "word": "esta", "tf": 0.1111111111111111, "idf": 2.0644579892269186 },
        {
          "word": "equipa",
          "tf": 0.1111111111111111,
          "idf": 2.0644579892269186
        },
        {
          "word": "marca",
          "tf": 0.1111111111111111,
          "idf": 2.0644579892269186
        },
        { "word": "o", "tf": 0.2222222222222222, "idf": 1.2863067388432747 },
        {
          "word": "futuro",
          "tf": 0.2222222222222222,
          "idf": 2.0644579892269186
        },
        { "word": "está", "tf": 0.1111111111111111, "idf": 1.7634279935629373 },
        {
          "word": "assegurado",
          "tf": 0.1111111111111111,
          "idf": 2.0644579892269186
        }
      ]
    },
    {
      "sentence": "portugal espremeu a laranja mecânica as imagens do título",
      "words": [
        {
          "word": "portugal",
          "tf": 0.1111111111111111,
          "idf": 1.2863067388432747
        },
        {
          "word": "espremeu",
          "tf": 0.1111111111111111,
          "idf": 2.0644579892269186
        },
        { "word": "a", "tf": 0.1111111111111111, "idf": 1.3654879848908996 },
        {
          "word": "laranja",
          "tf": 0.1111111111111111,
          "idf": 2.0644579892269186
        },
        {
          "word": "mecânica",
          "tf": 0.1111111111111111,
          "idf": 2.0644579892269186
        },
        { "word": "as", "tf": 0.1111111111111111, "idf": 2.0644579892269186 },
        {
          "word": "imagens",
          "tf": 0.1111111111111111,
          "idf": 2.0644579892269186
        },
        { "word": "do", "tf": 0.1111111111111111, "idf": 2.0644579892269186 },
        {
          "word": "título",
          "tf": 0.1111111111111111,
          "idf": 2.0644579892269186
        }
      ]
    },
    {
      "sentence": "portugal levanta o troféu seleção conquista a liga das nações",
      "words": [
        { "word": "portugal", "tf": 0.1, "idf": 1.2863067388432747 },
        { "word": "levanta", "tf": 0.1, "idf": 2.0644579892269186 },
        { "word": "o", "tf": 0.1, "idf": 1.2863067388432747 },
        { "word": "troféu", "tf": 0.1, "idf": 2.0644579892269186 },
        { "word": "seleção", "tf": 0.1, "idf": 2.0644579892269186 },
        { "word": "conquista", "tf": 0.1, "idf": 1.7634279935629373 },
        { "word": "a", "tf": 0.1, "idf": 1.3654879848908996 },
        { "word": "liga", "tf": 0.1, "idf": 1.7634279935629373 },
        { "word": "das", "tf": 0.1, "idf": 1.7634279935629373 },
        { "word": "nações", "tf": 0.1, "idf": 1.7634279935629373 }
      ]
    },
    {
      "sentence": "a combinação entre bernardo e guedes eis o golo que deu vitória a portugal",
      "words": [
        { "word": "a", "tf": 0.14285714285714285, "idf": 1.3654879848908996 },
        {
          "word": "combinação",
          "tf": 0.07142857142857142,
          "idf": 2.0644579892269186
        },
        {
          "word": "entre",
          "tf": 0.07142857142857142,
          "idf": 2.0644579892269186
        },
        {
          "word": "bernardo",
          "tf": 0.07142857142857142,
          "idf": 2.0644579892269186
        },
        { "word": "e", "tf": 0.07142857142857142, "idf": 1.3654879848908996 },
        {
          "word": "guedes",
          "tf": 0.07142857142857142,
          "idf": 1.7634279935629373
        },
        { "word": "eis", "tf": 0.07142857142857142, "idf": 2.0644579892269186 },
        { "word": "o", "tf": 0.07142857142857142, "idf": 1.2863067388432747 },
        {
          "word": "golo",
          "tf": 0.07142857142857142,
          "idf": 2.0644579892269186
        },
        { "word": "que", "tf": 0.07142857142857142, "idf": 2.0644579892269186 },
        { "word": "deu", "tf": 0.07142857142857142, "idf": 2.0644579892269186 },
        {
          "word": "vitória",
          "tf": 0.07142857142857142,
          "idf": 2.0644579892269186
        },
        {
          "word": "portugal",
          "tf": 0.07142857142857142,
          "idf": 1.2863067388432747
        }
      ]
    },
    {
      "sentence": "joker guedes rematou para o ouro portugal conquista liga das nações",
      "words": [
        {
          "word": "joker",
          "tf": 0.09090909090909091,
          "idf": 2.0644579892269186
        },
        {
          "word": "guedes",
          "tf": 0.09090909090909091,
          "idf": 1.7634279935629373
        },
        {
          "word": "rematou",
          "tf": 0.09090909090909091,
          "idf": 2.0644579892269186
        },
        {
          "word": "para",
          "tf": 0.09090909090909091,
          "idf": 1.3654879848908996
        },
        { "word": "o", "tf": 0.09090909090909091, "idf": 1.2863067388432747 },
        {
          "word": "ouro",
          "tf": 0.09090909090909091,
          "idf": 1.7634279935629373
        },
        {
          "word": "portugal",
          "tf": 0.09090909090909091,
          "idf": 1.2863067388432747
        },
        {
          "word": "conquista",
          "tf": 0.09090909090909091,
          "idf": 1.7634279935629373
        },
        {
          "word": "liga",
          "tf": 0.09090909090909091,
          "idf": 1.7634279935629373
        },
        { "word": "das", "tf": 0.09090909090909091, "idf": 1.7634279935629373 },
        {
          "word": "nações",
          "tf": 0.09090909090909091,
          "idf": 1.7634279935629373
        }
      ]
    },
    {
      "sentence": "ps ganha psd perde be sobe e pan elege um eurodeputado",
      "words": [
        { "word": "ps", "tf": 0.09090909090909091, "idf": 2.0644579892269186 },
        {
          "word": "ganha",
          "tf": 0.09090909090909091,
          "idf": 2.0644579892269186
        },
        { "word": "psd", "tf": 0.09090909090909091, "idf": 2.0644579892269186 },
        {
          "word": "perde",
          "tf": 0.09090909090909091,
          "idf": 2.0644579892269186
        },
        { "word": "be", "tf": 0.09090909090909091, "idf": 2.0644579892269186 },
        {
          "word": "sobe",
          "tf": 0.09090909090909091,
          "idf": 2.0644579892269186
        },
        { "word": "e", "tf": 0.09090909090909091, "idf": 1.3654879848908996 },
        { "word": "pan", "tf": 0.09090909090909091, "idf": 2.0644579892269186 },
        {
          "word": "elege",
          "tf": 0.09090909090909091,
          "idf": 2.0644579892269186
        },
        { "word": "um", "tf": 0.09090909090909091, "idf": 1.7634279935629373 },
        {
          "word": "eurodeputado",
          "tf": 0.09090909090909091,
          "idf": 2.0644579892269186
        }
      ]
    }
  ]
}
